<wpml-config>
	<admin-texts>
		<key name="site_reviews">
			<key name="settings">
				<key name="general">
					<key name="request_verification_message"/>
					<key name="notification_message"/>
				</key>
				<key name="reviews">
					<key name="date">
						<key name="custom"/>
					</key>
				</key>
				<key name="schema">
					<key name="name">
						<key name="custom"/>
					</key>
					<key name="description">
						<key name="custom"/>
					</key>
					<key name="pricecurrency"/>
				</key>
				<key name="strings">
					<key name="*">
						<key name="s2"/>
					</key>
				</key>
			</key>
		</key>
	</admin-texts>
	<custom-types>
		<custom-type translate="0">site-review</custom-type>
	</custom-types>
	<shortcodes>
		<shortcode>
			<tag>site_reviews</tag>
			<attributes>
				<attribute>fallback</attribute>
			</attributes>
		</shortcode>
		<shortcode>
			<tag>site_reviews_form</tag>
			<attributes>
				<attribute>description</attribute>
			</attributes>
		</shortcode>
		<shortcode>
			<tag>site_reviews_summary</tag>
			<attributes>
				<attribute>labels</attribute>
				<attribute>text</attribute>
			</attributes>
		</shortcode>
	</shortcodes>
</wpml-config>
